fieldfinder/__init__.py
fieldfinder/constants.py
fieldfinder/spectral_index.py
fieldfinder/utils.py
tests/__init__.py
tests/test_spectral_index.py
tests/test_utils.py
fieldfinder-0.1.1.dist-info/METADATA
fieldfinder-0.1.1.dist-info/WHEEL
fieldfinder-0.1.1.dist-info/top_level.txt
fieldfinder-0.1.1.dist-info/RECORD
