Metadata-Version: 2.1
Name: fieldfinder
Version: 0.1.1
Summary: Agricultural field detection using spectral indices and threshold masks.
Home-page: https://github.com/brendonhall/fieldfinder
Author: Brendon Hall
Author-email: brendon.hall@gmail.com
Requires-Python: >=3.6
Requires-Dist: numpy (>=1.10)
Requires-Dist: rasterio (>=1.3)
